devtracker_cli/__init__.py
devtracker_cli/cli.py
devtracker_cli/storage.py
devtracker_cli/tracker.py
devtracker_cli/utils.py
devtracker_cli/visualization.py
devtracker_cli-0.1.0.dist-info/METADATA
devtracker_cli-0.1.0.dist-info/WHEEL
devtracker_cli-0.1.0.dist-info/entry_points.txt
devtracker_cli-0.1.0.dist-info/top_level.txt
devtracker_cli-0.1.0.dist-info/RECORD
