Metadata-Version: 2.1
Name: devtracker-cli
Version: 0.1.0
Summary: A command-line tool to track development time and breaks
Home-page: https://github.com/aswinms926/devtracker-cli
Author: Aswin M S
Author-email: Aswin M S <deto2026@gmail.com>
Project-URL: Homepage, https://github.com/aswinms926/devtracker-cli
Keywords: development,time-tracking,productivity
Classifier: License :: OSI Approved :: MIT License
Classifier: Programming Language :: Python
Classifier: Programming Language :: Python :: 3
Requires-Python: >=3.6
Requires-Dist: click>=8.0.0
Requires-Dist: matplotlib>=3.5.0
Requires-Dist: numpy>=1.21.0
Provides-Extra: dev
Requires-Dist: pytest>=6.0.0; extra == "dev"
